odoo/addons/web_drop_target/README.rst
odoo/addons/web_drop_target/__init__.py
odoo/addons/web_drop_target/__manifest__.py
odoo/addons/web_drop_target/i18n/fr.po
odoo/addons/web_drop_target/i18n/web_drop_target.pot
odoo/addons/web_drop_target/readme/CONTRIBUTORS.rst
odoo/addons/web_drop_target/readme/DESCRIPTION.rst
odoo/addons/web_drop_target/readme/DEVELOP.rst
odoo/addons/web_drop_target/readme/ROADMAP.rst
odoo/addons/web_drop_target/readme/USAGE.rst
odoo/addons/web_drop_target/static/description/icon.png
odoo/addons/web_drop_target/static/description/index.html
odoo/addons/web_drop_target/static/description/screenshot.png
odoo/addons/web_drop_target/static/lib/base64js.min.js
odoo/addons/web_drop_target/static/src/js/web_drop_target.js
odoo/addons/web_drop_target/static/src/less/web_drop_target.less
odoo/addons/web_drop_target/static/src/xml/widgets.xml
odoo/addons/web_drop_target/views/templates.xml
odoo11_addon_web_drop_target-11.0.2.0.0.99.dev5.dist-info/METADATA
odoo11_addon_web_drop_target-11.0.2.0.0.99.dev5.dist-info/WHEEL
odoo11_addon_web_drop_target-11.0.2.0.0.99.dev5.dist-info/top_level.txt
odoo11_addon_web_drop_target-11.0.2.0.0.99.dev5.dist-info/RECORD
